mkdocs_iolanta/__init__.py
mkdocs_iolanta/_data/foaf/foaf.json
mkdocs_iolanta/_data/foaf/named-context.json
mkdocs_iolanta/_data/iolanta/named-context.json
mkdocs_iolanta/_data/octa/named-context.json
mkdocs_iolanta/_data/owl/named-context.json
mkdocs_iolanta/_data/owl/owl.json
mkdocs_iolanta/_data/rdf/named-context.json
mkdocs_iolanta/_data/rdf/rdf.json
mkdocs_iolanta/_data/rdfs/named-context.json
mkdocs_iolanta/_data/rdfs/rdfs.json
mkdocs_iolanta/_data/skos/named-context.json
mkdocs_iolanta/_data/skos/skos.json
mkdocs_iolanta/data/context.yaml
mkdocs_iolanta/data/material.yaml
mkdocs_iolanta/data/mkdocs.yaml
mkdocs_iolanta/facets/__init__.py
mkdocs_iolanta/facets/icon.py
mkdocs_iolanta/iolanta_plugin.py
mkdocs_iolanta/plugin.py
mkdocs_iolanta/sparql/template_per_page.sparql
mkdocs_iolanta-0.1.16.dist-info/LICENSE
mkdocs_iolanta-0.1.16.dist-info/METADATA
mkdocs_iolanta-0.1.16.dist-info/WHEEL
mkdocs_iolanta-0.1.16.dist-info/entry_points.txt
mkdocs_iolanta-0.1.16.dist-info/RECORD
