Metadata-Version: 2.1
Name: mkdocs-iolanta
Version: 0.1.16
Summary: MkDocs plugin to integrate with Iolanta semantic web framework.
License: MIT
Author: Anatoly Scherbakov
Author-email: altaisoft@gmail.com
Requires-Python: >=3.10,<3.12
Classifier: License :: OSI Approved :: MIT License
Classifier: Programming Language :: Python :: 3
Classifier: Programming Language :: Python :: 3.10
Classifier: Programming Language :: Python :: 3.11
Requires-Dist: iolanta (>=1.1.0)
Requires-Dist: mkdocs (>=1.4.2)
Requires-Dist: mkdocs-macros-plugin (>=0.7,<1.4)
